README.md
setup.cfg
setup.py
ElasticQuery.egg-info/PKG-INFO
ElasticQuery.egg-info/SOURCES.txt
ElasticQuery.egg-info/dependency_links.txt
ElasticQuery.egg-info/requires.txt
ElasticQuery.egg-info/top_level.txt
elasticquery/__init__.py
elasticquery/aggregates.py
elasticquery/dsl.py
elasticquery/dsl_util.py
elasticquery/elasticquery.py
elasticquery/exceptions.py
elasticquery/queries.py
elasticquery/suggesters.py