Metadata-Version: 1.0
Name: ElasticQuery
Version: 3.2
Summary: A simple query builder for Elasticsearch 2
Home-page: http://github.com/Fizzadar/ElasticQuery
Author: Nick Barrett
Author-email: pointlessrambler@gmail.com
License: UNKNOWN
Platform: UNKNOWN
